{"data_time": 0.24174923300006412, "eta_seconds": 925.2187444800802, "fast_rcnn/cls_accuracy": 0.7265625, "fast_rcnn/false_negative": 0.96875, "fast_rcnn/fg_cls_accuracy": 0.03125, "iteration": 19, "loss_box_reg": 0.282477930188179, "loss_cls": 0.6363094449043274, "loss_mask": 0.6912556290626526, "loss_rpn_cls": 0.8257172107696533, "loss_rpn_loc": 0.3069945424795151, "lr": 9.7405e-06, "mask_rcnn/accuracy": 0.6130022321428572, "mask_rcnn/false_negative": 0.0, "mask_rcnn/false_positive": 1.0, "rank_data_time": 0.24174923300006412, "roi_head/num_bg_samples": 24.0, "roi_head/num_fg_samples": 8.0, "rpn/num_neg_anchors": 128.0, "rpn/num_pos_anchors": 128.0, "time": 1.927539051000167, "timetest": 12.0, "total_loss": 2.7528501003980637}
{"data_time": 0.24432802899991657, "eta_seconds": 884.8677391999354, "fast_rcnn/cls_accuracy": 0.75, "fast_rcnn/false_negative": 1.0, "fast_rcnn/fg_cls_accuracy": 0.0, "iteration": 39, "loss_box_reg": 0.3918709456920624, "loss_cls": 0.5733982622623444, "loss_mask": 0.6716778874397278, "loss_rpn_cls": 0.4039558172225952, "loss_rpn_loc": 0.296386256814003, "lr": 1.97305e-05, "mask_rcnn/accuracy": 0.5822305484693877, "mask_rcnn/false_negative": 0.0, "mask_rcnn/false_positive": 1.0, "rank_data_time": 0.24432802899991657, "roi_head/num_bg_samples": 24.0, "roi_head/num_fg_samples": 8.0, "rpn/num_neg_anchors": 128.0, "rpn/num_pos_anchors": 128.0, "time": 1.9211158445000365, "timetest": 12.0, "total_loss": 2.3932723850011826}
{"data_time": 0.24415705699948376, "eta_seconds": 843.821038940041, "fast_rcnn/cls_accuracy": 0.75, "fast_rcnn/false_negative": 1.0, "fast_rcnn/fg_cls_accuracy": 0.0, "iteration": 59, "loss_box_reg": 0.5865035057067871, "loss_cls": 0.5267569124698639, "loss_mask": 0.6388009190559387, "loss_rpn_cls": 0.3021279275417328, "loss_rpn_loc": 0.2769832909107208, "lr": 2.9720499999999998e-05, "mask_rcnn/accuracy": 0.7262436224489796, "mask_rcnn/false_negative": 0.008798704759874206, "mask_rcnn/false_positive": 0.6224231175373895, "rank_data_time": 0.24415705699948376, "roi_head/num_bg_samples": 24.0, "roi_head/num_fg_samples": 8.0, "rpn/num_neg_anchors": 128.0, "rpn/num_pos_anchors": 128.0, "time": 1.9048222714995973, "timetest": 12.0, "total_loss": 2.3156907707452774}
{"data_time": 0.24385843799973372, "eta_seconds": 803.3690490000026, "fast_rcnn/cls_accuracy": 0.75, "fast_rcnn/false_negative": 1.0, "fast_rcnn/fg_cls_accuracy": 0.0, "iteration": 79, "loss_box_reg": 0.5986951291561127, "loss_cls": 0.5144546627998352, "loss_mask": 0.5918334424495697, "loss_rpn_cls": 0.23591983318328857, "loss_rpn_loc": 0.30118729174137115, "lr": 3.9710500000000005e-05, "mask_rcnn/accuracy": 0.7884048150510203, "mask_rcnn/false_negative": 0.01851026263878293, "mask_rcnn/false_positive": 0.4490170237696819, "rank_data_time": 0.24385843799973372, "roi_head/num_bg_samples": 24.0, "roi_head/num_fg_samples": 8.0, "rpn/num_neg_anchors": 128.0, "rpn/num_pos_anchors": 128.0, "time": 1.901611766500082, "timetest": 12.0, "total_loss": 2.3070218712091446}
{"bbox/AP": NaN, "bbox/AP50": NaN, "bbox/AP75": NaN, "bbox/APl": NaN, "bbox/APm": NaN, "bbox/APs": NaN, "data_time": 0.2410072415000286, "eta_seconds": 762.5016539999706, "fast_rcnn/cls_accuracy": 0.75, "fast_rcnn/false_negative": 1.0, "fast_rcnn/fg_cls_accuracy": 0.0, "iteration": 99, "loss_box_reg": 0.6634575426578522, "loss_cls": 0.4925229847431183, "loss_mask": 0.538196325302124, "loss_rpn_cls": 0.2117781788110733, "loss_rpn_loc": 0.22798513621091843, "lr": 4.97005e-05, "mask_rcnn/accuracy": 0.8142538265306123, "mask_rcnn/false_negative": 0.024800734814215734, "mask_rcnn/false_positive": 0.36925177193946235, "rank_data_time": 0.2410072415000286, "roi_head/num_bg_samples": 24.0, "roi_head/num_fg_samples": 8.0, "rpn/num_neg_anchors": 128.0, "rpn/num_pos_anchors": 128.0, "time": 1.89151443549963, "timetest": 12.0, "total_loss": 2.196674808859825, "validation_loss": 2.225157305598259}
{"data_time": 0.24167670299993915, "eta_seconds": 722.6734475900867, "fast_rcnn/cls_accuracy": 0.75, "fast_rcnn/false_negative": 1.0, "fast_rcnn/fg_cls_accuracy": 0.0, "iteration": 119, "loss_box_reg": 0.6675496101379395, "loss_cls": 0.4789269268512726, "loss_mask": 0.49071645736694336, "loss_rpn_cls": 0.19934877753257751, "loss_rpn_loc": 0.2441626340150833, "lr": 5.96905e-05, "mask_rcnn/accuracy": 0.8289421237244898, "mask_rcnn/false_negative": 0.033860562226545377, "mask_rcnn/false_positive": 0.3348942984645529, "rank_data_time": 0.24167670299993915, "roi_head/num_bg_samples": 24.0, "roi_head/num_fg_samples": 8.0, "rpn/num_neg_anchors": 128.0, "rpn/num_pos_anchors": 128.0, "time": 1.8866694305002056, "timetest": 12.0, "total_loss": 2.0590135902166367}
{"data_time": 0.24047500849974313, "eta_seconds": 683.2696206600485, "fast_rcnn/cls_accuracy": 0.76171875, "fast_rcnn/false_negative": 0.9375, "fast_rcnn/fg_cls_accuracy": 0.0625, "iteration": 139, "loss_box_reg": 0.6748188138008118, "loss_cls": 0.4649864435195923, "loss_mask": 0.44195809960365295, "loss_rpn_cls": 0.16446419060230255, "loss_rpn_loc": 0.26954011619091034, "lr": 6.96805e-05, "mask_rcnn/accuracy": 0.8427734375, "mask_rcnn/false_negative": 0.04579545209240879, "mask_rcnn/false_positive": 0.28459344435933787, "rank_data_time": 0.24047500849974313, "roi_head/num_bg_samples": 24.0, "roi_head/num_fg_samples": 8.0, "rpn/num_neg_anchors": 128.0, "rpn/num_pos_anchors": 128.0, "time": 1.8843361989997902, "timetest": 12.0, "total_loss": 2.021611623466015}
{"data_time": 0.24121033599976727, "eta_seconds": 644.5939629801978, "fast_rcnn/cls_accuracy": 0.78125, "fast_rcnn/false_negative": 0.828125, "fast_rcnn/fg_cls_accuracy": 0.171875, "iteration": 159, "loss_box_reg": 0.6843692064285278, "loss_cls": 0.44017288088798523, "loss_mask": 0.3943491280078888, "loss_rpn_cls": 0.1715354472398758, "loss_rpn_loc": 0.24379274249076843, "lr": 7.967050000000001e-05, "mask_rcnn/accuracy": 0.8574617346938775, "mask_rcnn/false_negative": 0.054431685299714254, "mask_rcnn/false_positive": 0.2509973818595489, "rank_data_time": 0.24121033599976727, "roi_head/num_bg_samples": 24.0, "roi_head/num_fg_samples": 8.0, "rpn/num_neg_anchors": 128.0, "rpn/num_pos_anchors": 128.0, "time": 1.8822139425001296, "timetest": 12.0, "total_loss": 1.960659697651863}
{"data_time": 0.2453716949999034, "eta_seconds": 606.2459521600977, "fast_rcnn/cls_accuracy": 0.80078125, "fast_rcnn/false_negative": 0.6875, "fast_rcnn/fg_cls_accuracy": 0.3125, "iteration": 179, "loss_box_reg": 0.641455739736557, "loss_cls": 0.4215356856584549, "loss_mask": 0.3465568423271179, "loss_rpn_cls": 0.1583217903971672, "loss_rpn_loc": 0.26658643782138824, "lr": 8.966049999999999e-05, "mask_rcnn/accuracy": 0.8711933992346939, "mask_rcnn/false_negative": 0.07014356349267473, "mask_rcnn/false_positive": 0.1980880420118546, "rank_data_time": 0.2453716949999034, "roi_head/num_bg_samples": 24.0, "roi_head/num_fg_samples": 8.0, "rpn/num_neg_anchors": 128.0, "rpn/num_pos_anchors": 128.0, "time": 1.889572199000213, "timetest": 12.0, "total_loss": 1.8219085559248924}
{"bbox/AP": 17.997023557069088, "bbox/AP-Cluster": 0.0, "bbox/AP-Macrophage": 35.99404711413818, "bbox/AP50": 32.42011094827565, "bbox/AP75": 17.23421597983046, "bbox/APl": 17.902198898181762, "bbox/APm": 40.68896889688969, "bbox/APs": NaN, "data_time": 0.24414615449995836, "eta_seconds": 568.310949600118, "fast_rcnn/cls_accuracy": 0.81640625, "fast_rcnn/false_negative": 0.609375, "fast_rcnn/fg_cls_accuracy": 0.390625, "iteration": 199, "loss_box_reg": 0.6493554711341858, "loss_cls": 0.4004516154527664, "loss_mask": 0.3084367662668228, "loss_rpn_cls": 0.14847010374069214, "loss_rpn_loc": 0.2514250725507736, "lr": 9.96505e-05, "mask_rcnn/accuracy": 0.887954400510204, "mask_rcnn/false_negative": 0.07347162941064725, "mask_rcnn/false_positive": 0.16013610678245493, "rank_data_time": 0.24414615449995836, "roi_head/num_bg_samples": 24.0, "roi_head/num_fg_samples": 8.0, "rpn/num_neg_anchors": 128.0, "rpn/num_pos_anchors": 128.0, "segm/AP": 21.903477298559956, "segm/AP-Cluster": 0.0, "segm/AP-Macrophage": 43.80695459711991, "segm/AP50": 34.04436485075425, "segm/AP75": 26.748110565114413, "segm/APl": 22.97445694532415, "segm/APm": 29.775769801060374, "segm/APs": NaN, "time": 1.8923972155002957, "timetest": 12.0, "total_loss": 1.7886616736650467, "validation_loss": 1.8820313662290573}
{"data_time": 0.2432155490000696, "eta_seconds": 530.3642299199964, "fast_rcnn/cls_accuracy": 0.83984375, "fast_rcnn/false_negative": 0.5, "fast_rcnn/fg_cls_accuracy": 0.5, "iteration": 219, "loss_box_reg": 0.5930328667163849, "loss_cls": 0.38085387647151947, "loss_mask": 0.2848527729511261, "loss_rpn_cls": 0.1359117478132248, "loss_rpn_loc": 0.22755160927772522, "lr": 0.00010964050000000001, "mask_rcnn/accuracy": 0.8846659757653061, "mask_rcnn/false_negative": 0.08701809846797878, "mask_rcnn/false_positive": 0.14677499997545887, "rank_data_time": 0.2432155490000696, "roi_head/num_bg_samples": 24.0, "roi_head/num_fg_samples": 8.0, "rpn/num_neg_anchors": 128.0, "rpn/num_pos_anchors": 128.0, "time": 1.8924400115001845, "timetest": 12.0, "total_loss": 1.6659897789359093}
{"data_time": 0.24228571699995882, "eta_seconds": 492.28364939008316, "fast_rcnn/cls_accuracy": 0.8125, "fast_rcnn/false_negative": 0.484375, "fast_rcnn/fg_cls_accuracy": 0.515625, "iteration": 239, "loss_box_reg": 0.6122011244297028, "loss_cls": 0.40330909192562103, "loss_mask": 0.2702505439519882, "loss_rpn_cls": 0.12925244867801666, "loss_rpn_loc": 0.2045900821685791, "lr": 0.0001196305, "mask_rcnn/accuracy": 0.8850645727040816, "mask_rcnn/false_negative": 0.09927362967642854, "mask_rcnn/false_positive": 0.12128562849234947, "rank_data_time": 0.24228571699995882, "roi_head/num_bg_samples": 24.0, "roi_head/num_fg_samples": 8.0, "rpn/num_neg_anchors": 128.0, "rpn/num_pos_anchors": 128.0, "time": 1.8894443344997853, "timetest": 12.0, "total_loss": 1.6884697377681732}
{"data_time": 0.2432982495001852, "eta_seconds": 454.5346802399945, "fast_rcnn/cls_accuracy": 0.84375, "fast_rcnn/false_negative": 0.40625, "fast_rcnn/fg_cls_accuracy": 0.59375, "iteration": 259, "loss_box_reg": 0.5605033040046692, "loss_cls": 0.34884126484394073, "loss_mask": 0.25151753425598145, "loss_rpn_cls": 0.12540893629193306, "loss_rpn_loc": 0.25245869159698486, "lr": 0.0001296205, "mask_rcnn/accuracy": 0.8921396683673469, "mask_rcnn/false_negative": 0.09857096929716103, "mask_rcnn/false_positive": 0.12057299338128012, "rank_data_time": 0.2432982495001852, "roi_head/num_bg_samples": 24.0, "roi_head/num_fg_samples": 8.0, "rpn/num_neg_anchors": 128.0, "rpn/num_pos_anchors": 128.0, "time": 1.8962735310001335, "timetest": 12.0, "total_loss": 1.5211827494204044}
{"data_time": 0.2422171225002785, "eta_seconds": 416.6605024999535, "fast_rcnn/cls_accuracy": 0.8515625, "fast_rcnn/false_negative": 0.375, "fast_rcnn/fg_cls_accuracy": 0.625, "iteration": 279, "loss_box_reg": 0.5418072044849396, "loss_cls": 0.34492671489715576, "loss_mask": 0.2663941979408264, "loss_rpn_cls": 0.11936086788773537, "loss_rpn_loc": 0.22592797875404358, "lr": 0.00013961050000000003, "mask_rcnn/accuracy": 0.8822146045918366, "mask_rcnn/false_negative": 0.11704081804610703, "mask_rcnn/false_positive": 0.117360623804319, "rank_data_time": 0.2422171225002785, "roi_head/num_bg_samples": 24.0, "roi_head/num_fg_samples": 8.0, "rpn/num_neg_anchors": 128.0, "rpn/num_pos_anchors": 128.0, "time": 1.8949231060000784, "timetest": 12.0, "total_loss": 1.5278185904026031}
{"bbox/AP": 23.063191755125928, "bbox/AP-Cluster": 0.0, "bbox/AP-Macrophage": 46.12638351025185, "bbox/AP50": 38.618979644400795, "bbox/AP75": 24.19855361024598, "bbox/APl": 23.122828417484754, "bbox/APm": 51.98019801980198, "bbox/APs": NaN, "data_time": 0.24231709800005774, "eta_seconds": 378.78227499995774, "fast_rcnn/cls_accuracy": 0.84765625, "fast_rcnn/false_negative": 0.359375, "fast_rcnn/fg_cls_accuracy": 0.640625, "iteration": 299, "loss_box_reg": 0.47925880551338196, "loss_cls": 0.3329347223043442, "loss_mask": 0.24056773632764816, "loss_rpn_cls": 0.1282920017838478, "loss_rpn_loc": 0.22908701747655869, "lr": 0.0001496005, "mask_rcnn/accuracy": 0.8971221301020409, "mask_rcnn/false_negative": 0.10174339537555548, "mask_rcnn/false_positive": 0.10343146769668683, "rank_data_time": 0.24231709800005774, "roi_head/num_bg_samples": 24.0, "roi_head/num_fg_samples": 8.0, "rpn/num_neg_anchors": 128.0, "rpn/num_pos_anchors": 128.0, "segm/AP": 25.482469840515392, "segm/AP-Cluster": 0.0, "segm/AP-Macrophage": 50.964939681030785, "segm/AP50": 39.34029385041852, "segm/AP75": 32.07819786339964, "segm/APl": 26.539615069620393, "segm/APm": 31.64120221177359, "segm/APs": NaN, "time": 1.8945126224998603, "timetest": 12.0, "total_loss": 1.4130570590496063, "validation_loss": 1.4928677454590797}
{"data_time": 0.24339676750014405, "eta_seconds": 340.90404749996196, "fast_rcnn/cls_accuracy": 0.87109375, "fast_rcnn/false_negative": 0.328125, "fast_rcnn/fg_cls_accuracy": 0.671875, "iteration": 319, "loss_box_reg": 0.4705047309398651, "loss_cls": 0.29880306124687195, "loss_mask": 0.23689010739326477, "loss_rpn_cls": 0.10818741843104362, "loss_rpn_loc": 0.23922669142484665, "lr": 0.0001595905, "mask_rcnn/accuracy": 0.8963847257653061, "mask_rcnn/false_negative": 0.09745869641058391, "mask_rcnn/false_positive": 0.11197082529329312, "rank_data_time": 0.24339676750014405, "roi_head/num_bg_samples": 24.0, "roi_head/num_fg_samples": 8.0, "rpn/num_neg_anchors": 128.0, "rpn/num_pos_anchors": 128.0, "time": 1.8934317289999854, "timetest": 12.0, "total_loss": 1.383066140115261}
{"data_time": 0.24549291049970634, "eta_seconds": 303.08087816003535, "fast_rcnn/cls_accuracy": 0.8671875, "fast_rcnn/false_negative": 0.3125, "fast_rcnn/fg_cls_accuracy": 0.6875, "iteration": 339, "loss_box_reg": 0.4432465434074402, "loss_cls": 0.3018435537815094, "loss_mask": 0.24225187301635742, "loss_rpn_cls": 0.100480817258358, "loss_rpn_loc": 0.20851954817771912, "lr": 0.00016958050000000002, "mask_rcnn/accuracy": 0.8929368622448979, "mask_rcnn/false_negative": 0.0985995728373319, "mask_rcnn/false_positive": 0.12339354067311994, "rank_data_time": 0.24549291049970634, "roi_head/num_bg_samples": 24.0, "roi_head/num_fg_samples": 8.0, "rpn/num_neg_anchors": 128.0, "rpn/num_pos_anchors": 128.0, "time": 1.9036245234997295, "timetest": 12.0, "total_loss": 1.3076057396829128}
{"data_time": 0.24279801199963913, "eta_seconds": 265.2288057300393, "fast_rcnn/cls_accuracy": 0.875, "fast_rcnn/false_negative": 0.28125, "fast_rcnn/fg_cls_accuracy": 0.71875, "iteration": 359, "loss_box_reg": 0.42705339193344116, "loss_cls": 0.28372690081596375, "loss_mask": 0.23917441815137863, "loss_rpn_cls": 0.10903733223676682, "loss_rpn_loc": 0.21472139656543732, "lr": 0.0001795705, "mask_rcnn/accuracy": 0.8933354591836735, "mask_rcnn/false_negative": 0.09996833058084292, "mask_rcnn/false_positive": 0.11343182132844633, "rank_data_time": 0.24279801199963913, "roi_head/num_bg_samples": 24.0, "roi_head/num_fg_samples": 8.0, "rpn/num_neg_anchors": 128.0, "rpn/num_pos_anchors": 128.0, "time": 1.9047929500002283, "timetest": 12.0, "total_loss": 1.2858015485107899}
{"data_time": 0.2410789524997199, "eta_seconds": 227.3389763400337, "fast_rcnn/cls_accuracy": 0.875, "fast_rcnn/false_negative": 0.265625, "fast_rcnn/fg_cls_accuracy": 0.734375, "iteration": 379, "loss_box_reg": 0.40035513043403625, "loss_cls": 0.2887997031211853, "loss_mask": 0.2376479133963585, "loss_rpn_cls": 0.10136178880929947, "loss_rpn_loc": 0.22433516383171082, "lr": 0.0001895605, "mask_rcnn/accuracy": 0.8948501275510204, "mask_rcnn/false_negative": 0.10121281243728969, "mask_rcnn/false_positive": 0.1090665853061289, "rank_data_time": 0.2410789524997199, "roi_head/num_bg_samples": 24.0, "roi_head/num_fg_samples": 8.0, "rpn/num_neg_anchors": 128.0, "rpn/num_pos_anchors": 128.0, "time": 1.8941272709998884, "timetest": 12.0, "total_loss": 1.2458160482347012}
{"bbox/AP": 25.579890055449194, "bbox/AP-Cluster": 0.0, "bbox/AP-Macrophage": 51.15978011089839, "bbox/AP50": 39.91134340942976, "bbox/AP75": 28.495088356923915, "bbox/APl": 25.809765625102628, "bbox/APm": 52.772277227722775, "bbox/APs": NaN, "data_time": 0.24185502099953737, "eta_seconds": 189.44914695002808, "fast_rcnn/cls_accuracy": 0.890625, "fast_rcnn/false_negative": 0.25, "fast_rcnn/fg_cls_accuracy": 0.75, "iteration": 399, "loss_box_reg": 0.4239969849586487, "loss_cls": 0.25636616349220276, "loss_mask": 0.24031201750040054, "loss_rpn_cls": 0.09341509640216827, "loss_rpn_loc": 0.21825352311134338, "lr": 0.00019955050000000003, "mask_rcnn/accuracy": 0.8954679528061225, "mask_rcnn/false_negative": 0.09765125812400974, "mask_rcnn/false_positive": 0.11644082430246028, "rank_data_time": 0.24185502099953737, "roi_head/num_bg_samples": 24.0, "roi_head/num_fg_samples": 8.0, "rpn/num_neg_anchors": 128.0, "rpn/num_pos_anchors": 128.0, "segm/AP": 27.01339543801468, "segm/AP-Cluster": 0.0, "segm/AP-Macrophage": 54.02679087602936, "segm/AP50": 40.38313882811222, "segm/AP75": 34.49889451106324, "segm/APl": 27.850060049475523, "segm/APm": 35.58153258683426, "segm/APs": NaN, "time": 1.8913882555002601, "timetest": 12.0, "total_loss": 1.1986767426133156, "validation_loss": 1.4266785476356745}
{"data_time": 0.23900513199987472, "eta_seconds": 151.5536760800387, "fast_rcnn/cls_accuracy": 0.88671875, "fast_rcnn/false_negative": 0.25, "fast_rcnn/fg_cls_accuracy": 0.75, "iteration": 419, "loss_box_reg": 0.39843884110450745, "loss_cls": 0.2592865228652954, "loss_mask": 0.21938371658325195, "loss_rpn_cls": 0.08553513884544373, "loss_rpn_loc": 0.19567329436540604, "lr": 0.00020954049999999998, "mask_rcnn/accuracy": 0.904655612244898, "mask_rcnn/false_negative": 0.08693410228023696, "mask_rcnn/false_positive": 0.10121033870749693, "rank_data_time": 0.23900513199987472, "roi_head/num_bg_samples": 24.0, "roi_head/num_fg_samples": 8.0, "rpn/num_neg_anchors": 128.0, "rpn/num_pos_anchors": 128.0, "time": 1.891007177499887, "timetest": 12.0, "total_loss": 1.1843032911419868}
{"data_time": 0.2419504515000881, "eta_seconds": 113.66948817001685, "fast_rcnn/cls_accuracy": 0.89453125, "fast_rcnn/false_negative": 0.21875, "fast_rcnn/fg_cls_accuracy": 0.78125, "iteration": 439, "loss_box_reg": 0.37984152138233185, "loss_cls": 0.25197889655828476, "loss_mask": 0.2266983985900879, "loss_rpn_cls": 0.09003554284572601, "loss_rpn_loc": 0.19792811572551727, "lr": 0.0002195305, "mask_rcnn/accuracy": 0.901108099489796, "mask_rcnn/false_negative": 0.09078982522860547, "mask_rcnn/false_positive": 0.113508028717137, "rank_data_time": 0.2419504515000881, "roi_head/num_bg_samples": 24.0, "roi_head/num_fg_samples": 8.0, "rpn/num_neg_anchors": 128.0, "rpn/num_pos_anchors": 128.0, "time": 1.8966255054997418, "timetest": 12.0, "total_loss": 1.1430942676961422}
{"data_time": 0.24358517100017707, "eta_seconds": 75.7989276599983, "fast_rcnn/cls_accuracy": 0.8828125, "fast_rcnn/false_negative": 0.265625, "fast_rcnn/fg_cls_accuracy": 0.734375, "iteration": 459, "loss_box_reg": 0.3744536340236664, "loss_cls": 0.2622324824333191, "loss_mask": 0.23865896463394165, "loss_rpn_cls": 0.0911639891564846, "loss_rpn_loc": 0.21828226000070572, "lr": 0.00022952050000000002, "mask_rcnn/accuracy": 0.8958466198979592, "mask_rcnn/false_negative": 0.09764791645776147, "mask_rcnn/false_positive": 0.11067806870937538, "rank_data_time": 0.24358517100017707, "roi_head/num_bg_samples": 24.0, "roi_head/num_fg_samples": 8.0, "rpn/num_neg_anchors": 128.0, "rpn/num_pos_anchors": 128.0, "time": 1.9053839519997382, "timetest": 12.0, "total_loss": 1.2237120233476162}
{"data_time": 0.24168339700054275, "eta_seconds": 37.904396600006294, "fast_rcnn/cls_accuracy": 0.890625, "fast_rcnn/false_negative": 0.25, "fast_rcnn/fg_cls_accuracy": 0.75, "iteration": 479, "loss_box_reg": 0.37956804037094116, "loss_cls": 0.24743089079856873, "loss_mask": 0.22076762467622757, "loss_rpn_cls": 0.07682185620069504, "loss_rpn_loc": 0.16533411294221878, "lr": 0.0002395105, "mask_rcnn/accuracy": 0.9024035395408163, "mask_rcnn/false_negative": 0.08678697683443645, "mask_rcnn/false_positive": 0.10242172178199228, "rank_data_time": 0.24168339700054275, "roi_head/num_bg_samples": 24.0, "roi_head/num_fg_samples": 8.0, "rpn/num_neg_anchors": 128.0, "rpn/num_pos_anchors": 128.0, "time": 1.8999137269997846, "timetest": 12.0, "total_loss": 1.1073232516646385}
{"data_time": 0.24288967599977695, "eta_seconds": 0.0, "fast_rcnn/cls_accuracy": 0.87890625, "fast_rcnn/false_negative": 0.28125, "fast_rcnn/fg_cls_accuracy": 0.71875, "iteration": 499, "loss_box_reg": 0.38392364978790283, "loss_cls": 0.2442411482334137, "loss_mask": 0.22398429363965988, "loss_rpn_cls": 0.08975895866751671, "loss_rpn_loc": 0.19388489425182343, "lr": 0.0002495005, "mask_rcnn/accuracy": 0.9037986288265306, "mask_rcnn/false_negative": 0.0840377020321531, "mask_rcnn/false_positive": 0.10345685338531202, "rank_data_time": 0.24288967599977695, "roi_head/num_bg_samples": 24.0, "roi_head/num_fg_samples": 8.0, "rpn/num_neg_anchors": 128.0, "rpn/num_pos_anchors": 128.0, "time": 1.898018495499855, "timetest": 12.0, "total_loss": 1.1200605183839798, "validation_loss": 1.359758298844099}
{"bbox/AP": 26.631408264914818, "bbox/AP-Cluster": 0.0, "bbox/AP-Macrophage": 53.262816529829635, "bbox/AP50": 40.051815800842746, "bbox/AP75": 31.418612379931577, "bbox/APl": 26.890102107778613, "bbox/APm": 51.26966542808128, "bbox/APs": NaN, "iteration": 500, "segm/AP": 27.33926431033525, "segm/AP-Cluster": 0.0, "segm/AP-Macrophage": 54.6785286206705, "segm/AP50": 40.49178983215054, "segm/AP75": 35.96841355853776, "segm/APl": 28.044627887105122, "segm/APm": 35.841396219102535, "segm/APs": NaN}
